README
setup.py
bambu_markup/__init__.py
bambu_markup.egg-info/PKG-INFO
bambu_markup.egg-info/SOURCES.txt
bambu_markup.egg-info/dependency_links.txt
bambu_markup.egg-info/requires.txt
bambu_markup.egg-info/top_level.txt
bambu_markup/templatetags/__init__.py
bambu_markup/templatetags/markup.py