Metadata-Version: 1.1
Name: bambu-markup
Version: 2.0
Summary: Replacements for Django's Markdown and reStructuredText support
Home-page: https://github.com/iamsteadman/bambu-markup
Author: Steadman
Author-email: mark@steadman.io
License: UNKNOWN
Platform: UNKNOWN
Classifier: Development Status :: 4 - Beta
Classifier: Environment :: Web Environment
Classifier: Framework :: Django
